MANIFEST.in
README.rst
setup.py
feaas/__init__.py
feaas/api.py
feaas/auth.py
feaas/plugin.py
feaas/storage.py
feaas/managers/__init__.py
feaas/managers/cloudstack.py
feaas/managers/cloudstack_client.py
feaas/managers/ec2.py
feaas/misc/default.vcl
feaas/misc/dump_vcls.bash
feaas/runners/__init__.py
feaas/runners/instance_scalator.py
feaas/runners/instance_starter.py
feaas/runners/instance_terminator.py
feaas/runners/vcl_writer.py
tsuru_feaas.egg-info/PKG-INFO
tsuru_feaas.egg-info/SOURCES.txt
tsuru_feaas.egg-info/dependency_links.txt
tsuru_feaas.egg-info/requires.txt
tsuru_feaas.egg-info/top_level.txt