Metadata-Version: 1.1
Name: tsuru-feaas
Version: 0.9.4
Summary: Frontend as-a-service API for Tsuru PaaS
Home-page: UNKNOWN
Author: Tsuru
Author-email: tsuru@corp.globo.com
License: UNKNOWN
Platform: UNKNOWN
Classifier: Programming Language :: Python :: 2.7
